CHANGELOG.txt
LICENSE.txt
MANIFEST.in
README.txt
setup.py
etchkay/__init__.py
etchkay.egg-info/PKG-INFO
etchkay.egg-info/SOURCES.txt
etchkay.egg-info/dependency_links.txt
etchkay.egg-info/requires.txt
etchkay.egg-info/top_level.txt