Metadata-Version: 2.1
Name: etchkay
Version: 0.0.1
Summary: A compressed way to data science and analytics path
Home-page: 
Author: Hamza Khalid
Author-email: hamzakhalidd@outlook.com
License: MIT
Keywords: etchkay
Classifier: Development Status :: 5 - Production/Stable
Classifier: Intended Audience :: Education
Classifier: Operating System :: Microsoft :: Windows :: Windows 10
Classifier: License :: OSI Approved :: MIT License
Classifier: Programming Language :: Python :: 3
License-File: LICENSE.txt
